pdfcipher/__init__.py
pdfcipher/helpers.py
pdfcipher/qpdf.py
pdfcipher/vars.py
pdfcipher-1.0.1.dist-info/METADATA
pdfcipher-1.0.1.dist-info/WHEEL
pdfcipher-1.0.1.dist-info/entry_points.txt
pdfcipher-1.0.1.dist-info/top_level.txt
pdfcipher-1.0.1.dist-info/RECORD
