Metadata-Version: 2.2
Name: pdfcipher
Version: 1.0.1
Summary: A command-line tool for encrypting and decrypting PDF files with password protection.
Author: James Cherti
License: GPL-3.0-or-later
Project-URL: Homepage, https://github.com/jamescherti/pdfcipher
Classifier: Development Status :: 5 - Production/Stable
Classifier: License :: OSI Approved :: GNU General Public License (GPL)
Classifier: License :: OSI Approved :: GNU General Public License v3 (GPLv3)
Classifier: Environment :: Console
Classifier: Operating System :: POSIX :: Linux
Classifier: Operating System :: POSIX :: Other
Classifier: Intended Audience :: Developers
Classifier: Intended Audience :: System Administrators
Classifier: Intended Audience :: End Users/Desktop
Classifier: Programming Language :: Python :: 3
Classifier: Topic :: Security :: Cryptography
Classifier: Topic :: Utilities
Requires-Python: <4,>=3.6
